{"paths":{},"types":[],"uuids":["d44ySS+RxLRIl1xGwT1JVU","1d+UuPrkFOg5k6GnVmTdcc","a8Anh32NZGRZegUtSgEj26","6eMtzwHBlOOqNbpE7XVasp","9aVStaOc9I4Lz/BmloIG8K","40/87P6xVAG4Ex2M/vaXP4","210Z/kztNAgaZLhw6G2ko8","6aoKpq6+5BVaCIpoemqt7E","a89tgE4SNEgYU5ERO2lzLs","46RMwDNotEILi700T33CDt","83KVd9hFBE34M542w/Kp/s","adAshxdtpH9Zf1EP+ybanU","60axL/kCpHS6ndfijuRjKA","8f+NUs2g1EBrBiFb3ShtG9","b8RAsmemBK1KXJTdKgDWHr","6ecH94T7VD8o/RcB/cc8gU","f4BUjqJI1PFa4UordxJhgH","4cPnhmYGZJc7K9728fDgU0","952SbBO4RM/IGqKq4QxzY2","2e/fqDTLJDj4MUimw97tzY","1dHvs/kYtGNra/aqDq+hU4","ecpdLyjvZBwrvm+cedCcQy","41D7kWhyFGY7q4NDlzkazn","43rQ8i/6lERbmHBpvMDL/E","07VqA1w2pP6ZedpOVani3N","389vQCfmFHLLCNfZdODVmH","8aJGlIxl5P7Z2BaoPVwpL9","330r51fThApaKDseLH24Ha","31vIlawANFZqnzLlSuHBfc","1ancSpaJdAvZbUWqBdcW1b","daYR/EXrRH+6faYshI5RYu","24ZcNoXmlDcJBS/mW1AvAh","47KCo4vkpFYKju07c/wFCr","2ahBdAVq5F/ZGhRs0qJIlf","73zCLfgaRJGIUqH0pZKdih","8bO+EjKqxG8Yy7oaj+K3b1","90TIAdG3JEUpjZaPIn4CRj","cfnCDV4iJFBZkL12s8SwW9","20ZAwCOMhAE6NnWShDUJzU","d9I38vcYhJ7YK8zXYSx4VN","9dGsPlrlFLWJsMUyG0Ic4n","0bSZjLwUBGapbEZUeUPkXQ","c4oeoXkU9C9YKGfmOde0U9","bbhDOc0hRErZ9prSJUhxC2","81yfRgu8lMLpVbl6FE8kRA"],"scenes":{"db://assets/Scene/game.fire":0},"redirect":[21,0],"deps":["internal"],"packs":{"077edbe5c":[24,41,29,1,38,31,33,28,27,25,22,23,32,34,44,26,35,36,40,43,42,37,0,39,30],"0bbadecfd":[20,6,19,5,9,17,12,7,3,15,10,13,18,4,2,8,11,14,16]},"name":"main","importBase":"import","nativeBase":"native","debug":false,"isZip":false,"encrypted":false,"versions":{"import":["077edbe5c","9bc17","0bbadecfd","3a47f"],"native":[20,"02cfd",1,"56736",6,"04f0f",19,"b26e8",5,"4974e",9,"4e321",17,"cf33f",12,"71077",7,"55ea4",3,"3bbdd",15,"d629b",10,"07c88",13,"82741",18,"6ffe8",4,"806e3",2,"cea68",8,"fe089",11,"d959c",14,"02f29",16,"cea6e"]}}